nova_post/__init__.py
nova_post/api.py
nova_post/exceptions.py
nova_post/logger.py
nova_post/adapters/__init__.py
nova_post/adapters/address.py
nova_post/adapters/common.py
nova_post/adapters/counterparty.py
nova_post/adapters/internet_document.py
nova_post/adapters/tracking.py
nova_post/models/__init__.py
nova_post/models/address.py
nova_post/models/common.py
nova_post/models/contact_person.py
nova_post/models/counterparty.py
nova_post/models/internet_document.py
nova_post/models/tracking.py
nova_post-0.2.3.dist-info/LICENSE
nova_post-0.2.3.dist-info/METADATA
nova_post-0.2.3.dist-info/WHEEL
nova_post-0.2.3.dist-info/top_level.txt
nova_post-0.2.3.dist-info/RECORD
