Metadata-Version: 2.2
Name: nova-post
Version: 0.2.3
Summary: Python SDK for working with the Nova Post API
Home-page: https://github.com/TrippyFrenemy/nova_post
Author: Dmytro Avrushchenko
Author-email: trippyfren@gmail.com
Classifier: Programming Language :: Python :: 3
Classifier: License :: OSI Approved :: MIT License
Classifier: Operating System :: OS Independent
Requires-Python: >=3.9
License-File: LICENSE
Requires-Dist: fake-useragent>=2.1.0
Requires-Dist: pydantic>=2.10.6
Requires-Dist: requests>=2.32.3
Dynamic: author
Dynamic: author-email
Dynamic: classifier
Dynamic: description
Dynamic: description-content-type
Dynamic: home-page
Dynamic: requires-dist
Dynamic: requires-python
Dynamic: summary
